ga/__init__.py
ga/__version__.py
ga/evolution.py
ga/individual.py
ga/population.py
generic_algorithm_light-0.2.1.dist-info/LICENSE
generic_algorithm_light-0.2.1.dist-info/METADATA
generic_algorithm_light-0.2.1.dist-info/WHEEL
generic_algorithm_light-0.2.1.dist-info/top_level.txt
generic_algorithm_light-0.2.1.dist-info/RECORD
