Metadata-Version: 2.1
Name: generic-algorithm-light
Version: 0.2.1
Summary: A lightweight genetic algorithm package for optimization
Author-email: Fernando Zepeda <fernando.zepeda@pm.me>
Classifier: Development Status :: 3 - Alpha
Classifier: Programming Language :: Python :: 3
Classifier: License :: OSI Approved :: MIT License
License-File: LICENSE
Requires-Dist: numpy >=1.22
Provides-Extra: dev
Requires-Dist: ruff ; extra == 'dev'
